cartuli/__init__.py
cartuli/__main__.py
cartuli/card.py
cartuli/deck.py
cartuli/definition.py
cartuli/filters.py
cartuli/measure.py
cartuli/output.py
cartuli/processing.py
cartuli/sheet.py
cartuli/template.py
cartuli-0.1.0b3.dist-info/LICENSE.txt
cartuli-0.1.0b3.dist-info/METADATA
cartuli-0.1.0b3.dist-info/WHEEL
cartuli-0.1.0b3.dist-info/entry_points.txt
cartuli-0.1.0b3.dist-info/top_level.txt
cartuli-0.1.0b3.dist-info/RECORD
