Metadata-Version: 2.1
Name: cartuli
Version: 0.1.0b3
Summary: A tool to create print and play card games
Home-page: https://github.com/pablerass/cartuli
Author: Pablo Muñoz
Author-email: pablerass@gmail.com
License: LGPLv3
Keywords: PnP card board game print
Classifier: Development Status :: 4 - Beta
Classifier: Environment :: Console
Classifier: Intended Audience :: End Users/Desktop
Classifier: License :: OSI Approved :: GNU Lesser General Public License v3 (LGPLv3)
Classifier: Operating System :: OS Independent
Classifier: Programming Language :: Python :: 3.10
Classifier: Programming Language :: Python :: 3.11
Classifier: Topic :: Games/Entertainment :: Board Games
Classifier: Typing :: Typed
Requires-Python: >=3.10
License-File: LICENSE.txt
Requires-Dist: reportlab ==4.*
Requires-Dist: opencv-python ==4.*
Requires-Dist: pillow ==10.*
Requires-Dist: pyyaml ==6.*
Requires-Dist: carpeta ==0.1.0a2
Requires-Dist: cairosvg ==2.*
Requires-Dist: lxml ==4.*
